README.rst
setup.py
django_langlink.egg-info/PKG-INFO
django_langlink.egg-info/SOURCES.txt
django_langlink.egg-info/dependency_links.txt
django_langlink.egg-info/pbr.json
django_langlink.egg-info/top_level.txt
langlink/__init__.py
langlink/admin.py
langlink/apps.py
langlink/models.py
langlink/tests.py
langlink/views.py
langlink/management/__init__.py
langlink/management/commands/__init__.py
langlink/management/commands/add_languages.py