Metadata-Version: 1.1
Name: django-langlink
Version: 0.1.2
Summary: Abstract language model and management command to populate language model
Home-page: https://github.com/payamnj/django-langlink
Author: Payam Najafizadeh
Author-email: payam.nj@gmail.com
License: New BSD
Platform: UNKNOWN
Classifier: Programming Language :: Python
Classifier: Operating System :: OS Independent
Classifier: Environment :: Web Environment
Classifier: Framework :: Django
Requires: django(>=1.8)
